gempy_engine/__init__.py
gempy_engine/_version.py
gempy_engine/config.py
gempy_engine/optional_dependencies.py
gempy_engine/API/__init__.py
gempy_engine/API/_version.py
gempy_engine/API/dual_contouring/__init__.py
gempy_engine/API/dual_contouring/_dual_contouring.py
gempy_engine/API/dual_contouring/_experimental_water_tight_DC_1.py
gempy_engine/API/dual_contouring/_interpolate_on_edges.py
gempy_engine/API/dual_contouring/_mask_buffer.py
gempy_engine/API/dual_contouring/multi_scalar_dual_contouring.py
gempy_engine/API/interp_single/__init__.py
gempy_engine/API/interp_single/_interp_scalar_field.py
gempy_engine/API/interp_single/_interp_single_feature.py
gempy_engine/API/interp_single/_multi_scalar_field_manager.py
gempy_engine/API/interp_single/_octree_generation.py
gempy_engine/API/interp_single/interp_features.py
gempy_engine/API/model/__init__.py
gempy_engine/API/model/model_api.py
gempy_engine/API/server/__init__.py
gempy_engine/API/server/_process_output.py
gempy_engine/API/server/_server_functions.py
gempy_engine/API/server/main_server_pro.py
gempy_engine/core/__init__.py
gempy_engine/core/backend_tensor.py
gempy_engine/core/utils.py
gempy_engine/core/data/__init__.py
gempy_engine/core/data/centered_grid.py
gempy_engine/core/data/continue_epoch.py
gempy_engine/core/data/custom_segmentation_functions.py
gempy_engine/core/data/dual_contouring_data.py
gempy_engine/core/data/dual_contouring_mesh.py
gempy_engine/core/data/engine_grid.py
gempy_engine/core/data/exported_fields.py
gempy_engine/core/data/exported_structs.py
gempy_engine/core/data/generic_grid.py
gempy_engine/core/data/geophysics_input.py
gempy_engine/core/data/input_data_descriptor.py
gempy_engine/core/data/internal_structs.py
gempy_engine/core/data/interp_output.py
gempy_engine/core/data/interpolation_functions.py
gempy_engine/core/data/interpolation_input.py
gempy_engine/core/data/matrices_sizes.py
gempy_engine/core/data/octree_level.py
gempy_engine/core/data/raw_arrays_solution.py
gempy_engine-2025.2.0.dist-info/licenses/AUTHORS.rst
gempy_engine-2025.2.0.dist-info/licenses/LICENSE
gempy_engine-2025.2.0.dist-info/METADATA
gempy_engine-2025.2.0.dist-info/WHEEL
gempy_engine-2025.2.0.dist-info/top_level.txt
gempy_engine-2025.2.0.dist-info/RECORD
