Metadata-Version: 2.4
Name: gempy_engine
Version: 2025.2.0
Summary: A Python package for GemPy
Home-page: https://github.com/gempy-project/gempy_engine
Author: Miguel de la Varga
Author-email: miguel@terranigma-solutions.com
License: EUPL-1.2
Classifier: Development Status :: 5 - Production/Stable
Classifier: Intended Audience :: Developers
Classifier: License :: OSI Approved :: European Union Public Licence 1.2 (EUPL 1.2)
Classifier: Operating System :: OS Independent
Classifier: Programming Language :: Python :: 3
Classifier: Programming Language :: Python :: 3.10
Classifier: Programming Language :: Python :: 3.11
Classifier: Programming Language :: Python :: 3.12
Requires-Python: >=3.10
License-File: LICENSE
License-File: AUTHORS.rst
Requires-Dist: numpy
Requires-Dist: pydantic
Requires-Dist: python-dotenv
Provides-Extra: dev
Requires-Dist: numpy; extra == "dev"
Requires-Dist: pydantic; extra == "dev"
Requires-Dist: python-dotenv; extra == "dev"
Requires-Dist: torch; extra == "dev"
Requires-Dist: matplotlib; extra == "dev"
Requires-Dist: pandas; extra == "dev"
Requires-Dist: pytest; extra == "dev"
Requires-Dist: pytest-benchmark; extra == "dev"
Requires-Dist: pytest-approvaltests; extra == "dev"
Provides-Extra: opt
Requires-Dist: numpy; extra == "opt"
Requires-Dist: pydantic; extra == "opt"
Requires-Dist: python-dotenv; extra == "opt"
Requires-Dist: torch; extra == "opt"
Provides-Extra: server
Requires-Dist: numpy; extra == "server"
Requires-Dist: pydantic; extra == "server"
Requires-Dist: python-dotenv; extra == "server"
Requires-Dist: torch; extra == "server"
Requires-Dist: fastapi; extra == "server"
Requires-Dist: uvicorn[standard]; extra == "server"
Requires-Dist: subsurface; extra == "server"
Requires-Dist: pandas; extra == "server"
Requires-Dist: httpx; extra == "server"
Requires-Dist: subsurface-terra; extra == "server"
Dynamic: author
Dynamic: author-email
Dynamic: classifier
Dynamic: description
Dynamic: description-content-type
Dynamic: home-page
Dynamic: license
Dynamic: license-file
Dynamic: provides-extra
Dynamic: requires-dist
Dynamic: requires-python
Dynamic: summary
